alpsplot/__init__.py
alpsplot/colormap.py
alpsplot/figure.py
alpsplot/optima.mplstyle
alpsplot/optima_bold.mplstyle
alpsplot/version.py
alpsplot/utils/__init__.py
alpsplot/utils/basic.py
alpsplot/utils/error_bar.py
alpsplot/utils/fit.py
alpsplot/utils/fonts/Optima-Bold.ttf
alpsplot/utils/fonts/Optima-BoldItalic.ttf
alpsplot/utils/fonts/Optima-ExtraBlack.ttf
alpsplot/utils/fonts/Optima-Italic.ttf
alpsplot/utils/fonts/Optima-Regular.ttf
alpsplot/utils/fonts/Palatino-Bold.ttf
alpsplot/utils/fonts/Palatino-BoldItalic.ttf
alpsplot/utils/fonts/Palatino-Italic.ttf
alpsplot/utils/fonts/Palatino-Roman.ttf
alpsplot/utils/fonts/__init__.py
alpsplot-1.2.0.dist-info/LICENSE
alpsplot-1.2.0.dist-info/METADATA
alpsplot-1.2.0.dist-info/WHEEL
alpsplot-1.2.0.dist-info/top_level.txt
alpsplot-1.2.0.dist-info/RECORD
